{"cameraMode":{"drawMode":0,"name":"Shaded","section":"Shading Mode"},"sceneLighting":false,"audioPlay":false,"sceneViewState":{"showFog":true,"showMaterialUpdate":false,"showSkybox":false,"showFlares":true,"showImageEffects":true,"showParticleSystems":true,"showVisualEffectGraphs":true,"m_FxEnabled":true},"in2DMode":false,"pivot":{"x":1.3102999925613404,"y":0.9847999811172485,"z":-3.911400079727173},"rotation":{"x":-0.10011893510818482,"y":0.7939299941062927,"z":-0.1361405998468399,"w":-0.5839950442314148},"size":0.014068841934204102,"orthographic":false}